passagemath_ntl/__init__.py
passagemath_ntl.libs/libgcc_s-0cd532bd.so.1
passagemath_ntl.libs/libgf2x-9e30c3e3.so.3.0.0
passagemath_ntl.libs/libgmp-0e7fc84e.so.10.5.0
passagemath_ntl.libs/libmpfi-a4c01d89.so.0.0.0
passagemath_ntl.libs/libmpfr-c0690335.so.6.2.2
passagemath_ntl.libs/libntl-2a4678f6.so.45.0.0
passagemath_ntl.libs/libstdc++-5d72f927.so.6.0.33
sage/all__sagemath_ntl.py
sage/libs/all__sagemath_ntl.py
sage/libs/mpfi/__init__.pxd
sage/libs/mpfi/types.pxd
sage/libs/ntl/GF2.pxd
sage/libs/ntl/GF2E.pxd
sage/libs/ntl/GF2EX.pxd
sage/libs/ntl/GF2X.pxd
sage/libs/ntl/ZZ.pxd
sage/libs/ntl/ZZX.pxd
sage/libs/ntl/ZZ_p.pxd
sage/libs/ntl/ZZ_pE.pxd
sage/libs/ntl/ZZ_pEX.pxd
sage/libs/ntl/ZZ_pX.pxd
sage/libs/ntl/__init__.py
sage/libs/ntl/all.py
sage/libs/ntl/conversion.pxd
sage/libs/ntl/convert.cpython-311-x86_64-linux-musl.so
sage/libs/ntl/convert.pxd
sage/libs/ntl/convert.pyx
sage/libs/ntl/decl.pxi
sage/libs/ntl/error.cpython-311-x86_64-linux-musl.so
sage/libs/ntl/error.pyx
sage/libs/ntl/lzz_p.pxd
sage/libs/ntl/lzz_pX.pxd
sage/libs/ntl/mat_GF2.pxd
sage/libs/ntl/mat_GF2E.pxd
sage/libs/ntl/mat_ZZ.pxd
sage/libs/ntl/misc.pxi
sage/libs/ntl/ntl_GF2.cpython-311-x86_64-linux-musl.so
sage/libs/ntl/ntl_GF2.pxd
sage/libs/ntl/ntl_GF2.pyx
sage/libs/ntl/ntl_GF2E.cpython-311-x86_64-linux-musl.so
sage/libs/ntl/ntl_GF2E.pxd
sage/libs/ntl/ntl_GF2E.pyx
sage/libs/ntl/ntl_GF2EContext.cpython-311-x86_64-linux-musl.so
sage/libs/ntl/ntl_GF2EContext.pxd
sage/libs/ntl/ntl_GF2EContext.pyx
sage/libs/ntl/ntl_GF2EX.cpython-311-x86_64-linux-musl.so
sage/libs/ntl/ntl_GF2EX.pxd
sage/libs/ntl/ntl_GF2EX.pyx
sage/libs/ntl/ntl_GF2X.cpython-311-x86_64-linux-musl.so
sage/libs/ntl/ntl_GF2X.pxd
sage/libs/ntl/ntl_GF2X.pyx
sage/libs/ntl/ntl_GF2X_linkage.pxi
sage/libs/ntl/ntl_ZZ.cpython-311-x86_64-linux-musl.so
sage/libs/ntl/ntl_ZZ.pxd
sage/libs/ntl/ntl_ZZ.pyx
sage/libs/ntl/ntl_ZZX.cpython-311-x86_64-linux-musl.so
sage/libs/ntl/ntl_ZZX.pxd
passagemath_ntl-10.6.43.dist-info/METADATA
passagemath_ntl-10.6.43.dist-info/WHEEL
passagemath_ntl-10.6.43.dist-info/top_level.txt
passagemath_ntl-10.6.43.dist-info/RECORD
